nonebot_plugin_smms/__init__.py
nonebot_plugin_smms/config.py
nonebot_plugin_smms/model.py
nonebot_plugin_smms/smms.py
nonebot_plugin_smms-0.1.0.dist-info/LICENSE
nonebot_plugin_smms-0.1.0.dist-info/METADATA
nonebot_plugin_smms-0.1.0.dist-info/WHEEL
nonebot_plugin_smms-0.1.0.dist-info/RECORD
