Metadata-Version: 2.1
Name: nonebot-plugin-smms
Version: 0.1.0
Summary: sm.ms 图床插件
Home-page: https://github.com/mobyw/nonebot-plugin-smms
License: MIT
Keywords: nonebot2,qq,plugin
Author: mobyw
Author-email: mobyw66@gmail.com
Requires-Python: >=3.8,<4.0
Classifier: License :: OSI Approved :: MIT License
Classifier: Programming Language :: Python :: 3
Classifier: Programming Language :: Python :: 3.8
Classifier: Programming Language :: Python :: 3.9
Classifier: Programming Language :: Python :: 3.10
Classifier: Programming Language :: Python :: 3.11
Requires-Dist: nonebot2[httpx] (>=2.1.2,<3.0.0)
Project-URL: Documentation, https://github.com/mobyw/nonebot-plugin-smms/blob/main/README.md
Project-URL: Repository, https://github.com/mobyw/nonebot-plugin-smms
